{
	"textures": [
		{
			"image": "assets.png",
			"format": "RGBA8888",
			"size": {
				"w": 48,
				"h": 24
			},
			"scale": 1,
			"frames": [
				{
					"filename": "heroes/test_hero/player_1.png",
					"rotated": false,
					"trimmed": false,
					"sourceSize": {
						"w": 24,
						"h": 24
					},
					"spriteSourceSize": {
						"x": 0,
						"y": 0,
						"w": 24,
						"h": 24
					},
					"frame": {
						"x": 0,
						"y": 0,
						"w": 24,
						"h": 24
					}
				},
				{
					"filename": "heroes/test_hero/player_2.png",
					"rotated": false,
					"trimmed": false,
					"sourceSize": {
						"w": 24,
						"h": 24
					},
					"spriteSourceSize": {
						"x": 0,
						"y": 0,
						"w": 24,
						"h": 24
					},
					"frame": {
						"x": 24,
						"y": 0,
						"w": 24,
						"h": 24
					}
				}
			]
		}
	],
	"meta": {
		"app": "https://www.codeandweb.com/texturepacker",
		"version": "3.0",
		"smartupdate": "$TexturePacker:SmartUpdate:93c5d2453b29327dcea94cee504ac53f:8e8c9e29803d64afb1acc60b36922e63:a759b6bbc8381ac9c472b28f589ad0d6$"
	}
}
